{
    "name": "Intf",
    "vendors": {
        "cisco": {
            "type": [
                "ios"
            ],
            "level": null
        }
    },
    "showCmds": [
        "sh run | sec ^interface"
    ],
    "keyCliLine": "interface (.+)",
    "rootEntryFlag": false,
    "mode": "basic",
    "boundaries": {
        "start": null
    },
    "discover": {
        "description": {
            "expressions": [
                "description\\s+(?<node>:N1:)(?<desc>.+)"
            ]
        }
    },
    "removeSyntax": {},
    "@exportedInstanceId": "610b977b-fe9c-4b7a-ae75-33fadff666c6",
    "@id": "610b977b-fe9c-4b7a-ae75-33fadff666c6",
    "@type": {
        "ref": "/sys/type/construct/global/conceptItem.jtype"
    },
    "@name": "IOS_Intf2_modified-ROM-Copy-2",
    "@description": ""
}