{
    "@type": {
        "ref": "/sys/type/construct/global/conceptItem.jtype"
    },
    "name": "Route",
    "showCmds": [
        "sh run | sec \"ip route\""
    ],
    "mode": "basic",
    "keyCliLine": "ip route .+",
    "rootEntryFlag": false,
    "boundaries": {
        "start": null
    },
    "discover": {},
    "removeSyntax": {},
    "vendors": {
        "cisco": {
            "type": [
                "nxos"
            ],
            "level": null
        }
    },
    "@source": {
        "instanceName": "NXOS_ipRoute"
    },
    "@exportedInstanceId": "c532ef82-00b4-4b27-b237-5b380f66b22b",
    "@id": "c532ef82-00b4-4b27-b237-5b380f66b22b",
    "@name": "NXOS_ipRoute",
    "@description": ""
}