{
    "@type": {
        "ref": "/sys/type/construct/domain/iosSwitchAssembly.jtype"
    },
    "domains": {
        "modules": {
            "aaa": {
                "policy": {
                    "@ref": "/org/instance/construct/feature/aaa/tacacs-step2.json"
                }
            }
        }
    },
    "interfaces": {
        "portMap": {
            "@ref": "/org/instance/construct/global/portMap/nyu-switch.json"
        }
    },
    "agents": {
        "watchdog": {}
    },
    "state": {
        "assessment": {
            "provision": {
                "policy": {
                    "@ref": "/org/instance/construct/global/cliStatePolicy/ping_tacacs-step2.json"
                },
                "schedule": "before",
                "action": "abort"
            }
        }
    },
    "@source": {
        "instanceName": "tacacs-migration-step2"
    },
    "@exportedInstanceId": "5929165a-0b68-4fd1-b821-889180cf4083",
    "@id": "5929165a-0b68-4fd1-b821-889180cf4083",
    "@name": "tacacs-migration-step2",
    "@description": ""
}