{
    "@type": {
        "ref": "/sys/type/construct/global/cliCommandGroup.jtype"
    },
    "regEx": "^bgp.+",
    "ignoreDelete": true,
    "cliBlocks": {
        "@ref": [
            "/org/instance/construct/global/cliCommands/nxos_bgp-cli.json"
        ]
    },
    "advanced": {},
    "maskCommands": [],
    "removeSyntax": {
        "list": []
    },
    "@source": {
        "instanceName": "nxos_bgp-group"
    },
    "@exportedInstanceId": "1ee50479-2800-4f33-a06c-ffc97ef34e08",
    "@id": "1ee50479-2800-4f33-a06c-ffc97ef34e08",
    "@name": "nxos_bgp-group",
    "@description": ""
}